[{"name":"Nikolayevsk-on-Amure","country":"RU","lat":53.1466,"lng":140.7229,"pop":27152,"capital":false},{"name":"Okha","country":"RU","lat":53.5949,"lng":142.9528,"pop":26560,"capital":false},{"name":"Aleksandrovsk-Sakhalinskiy","country":"RU","lat":50.8963,"lng":142.1634,"pop":12024,"capital":false},{"name":"Nogliki","country":"RU","lat":51.7968,"lng":143.1365,"pop":10098,"capital":false},{"name":"Tymovskoye","country":"RU","lat":50.8477,"lng":142.6626,"pop":8030,"capital":false},{"name":"Okhotsk","country":"RU","lat":59.362,"lng":143.2147,"pop":5570,"capital":false}]