[{"name":"Empalme","country":"MX","lat":27.9617,"lng":-110.8141,"pop":42516,"capital":false},{"name":"Ciudad Constitución","country":"MX","lat":25.0321,"lng":-111.6626,"pop":40935,"capital":false},{"name":"Miguel Alemán (La Doce)","country":"MX","lat":28.8403,"lng":-111.4775,"pop":30869,"capital":false},{"name":"Loreto","country":"MX","lat":26.0122,"lng":-111.3489,"pop":14724,"capital":false},{"name":"Pueblo Yaqui","country":"MX","lat":27.3552,"lng":-110.034,"pop":14234,"capital":false},{"name":"Guerrero Negro","country":"MX","lat":27.9601,"lng":-114.0559,"pop":13054,"capital":false},{"name":"Santa Rosalía","country":"MX","lat":27.3404,"lng":-112.2671,"pop":11765,"capital":false},{"name":"Vicam","country":"MX","lat":27.6431,"lng":-110.2946,"pop":8837,"capital":false},{"name":"Ciudad Insurgentes","country":"MX","lat":25.2635,"lng":-111.7744,"pop":8741,"capital":false},{"name":"San Luis","country":"MX","lat":28.4333,"lng":-113.75,"pop":7872,"capital":false},{"name":"San Ignacio Río Muerto","country":"MX","lat":27.4161,"lng":-110.2447,"pop":7718,"capital":false},{"name":"Pótam","country":"MX","lat":27.6258,"lng":-110.4177,"pop":7044,"capital":false},{"name":"Villa Alberto Andrés Alvarado Arámburo","country":"MX","lat":27.6444,"lng":-113.3847,"pop":6902,"capital":false},{"name":"Francisco Javier Mina","country":"MX","lat":27.4614,"lng":-110.1085,"pop":6242,"capital":false},{"name":"Bahía de Kino","country":"MX","lat":28.8228,"lng":-111.9408,"pop":6050,"capital":false},{"name":"Pesqueira","country":"MX","lat":29.3797,"lng":-110.8961,"pop":5699,"capital":false},{"name":"Puerto San Carlos","country":"MX","lat":24.7887,"lng":-112.105,"pop":5538,"capital":false},{"name":"Todos Santos","country":"MX","lat":23.4469,"lng":-110.2231,"pop":5148,"capital":false}]